Metadata-Version: 2.1
Name: pytest-ligo
Version: 0.0.1.dev23
Summary: Moved to https://yourlabs.io/oss/pytest-ligo
Home-page: https://yourlabs.io/oss/pytest-ligo
Author: James Pic
Author-email: jamespic@gmail.com
License: MIT
Keywords: cli ligo
Platform: UNKNOWN
Classifier: Development Status :: 4 - Beta
Classifier: Environment :: Console
Classifier: Environment :: Plugins
Classifier: Framework :: Pytest
Classifier: Intended Audience :: System Administrators
Classifier: License :: OSI Approved :: MIT License
Classifier: Operating System :: OS Independent
Classifier: Programming Language :: Python :: 3 :: Only
Classifier: Topic :: Software Development
Classifier: Topic :: System
Requires-Python: >=3
